{
    "copy"           : "AppSeed", 
    "email"          : "support@appseed.us",
    "design"         : "Highlights by Html5 UP",

    "app_title"      : "Eleventy Highlights",

    "seo_title"      : "Eleventy Highlights - Built with Automation Tools | AppSeed App Generator",
    "seo_desc"       : "Static Site prototyped in Eleventy SSG on top of Highlights Html5 Up design.",

    "product"        : "https://github.com/app-generator/eleventy-html5up-highlights", 
    "github"         : "https://github.com/app-generator/eleventy-html5up-highlights",
    "github_group"   : "https://github.com/app-generator/static-site",

    "docs"           : "https://docs.appseed.us/apps/static-site/eleventy-html5up-highlights/",
    "appseed"        : "https://appseed.us",      
    "generator"      : "https://appseed.us/app-generator",
    "blog"           : "https://blog.appseed.us/",
    "facebook"       : "https://facebook.com/webappseed",
    "twitter"        : "https://twitter.com/webappseed",
    "instagram"      : "https://instagram.com/webappseed",
    "support"        : "https://appseed.us/support",
    "discord"        : "https://discord.gg/fZC6hup",

    "LAST_KEY" : "NA"
}
